numeprimos/__init__.py
numeprimos-1.0.dist-info/LICENSE
numeprimos-1.0.dist-info/METADATA
numeprimos-1.0.dist-info/WHEEL
numeprimos-1.0.dist-info/top_level.txt
numeprimos-1.0.dist-info/RECORD
