Metadata-Version: 2.1
Name: numeprimos
Version: 1.0
Summary: Utilidad para calcular números primos.
Home-page: UNKNOWN
Author: Pablo Ruiz Vedia
Author-email: pabloruizve+python@gmail.com
License: GNU GPLv3
Keywords: numeros primos mathematical operations
Platform: UNKNOWN
Classifier: Development Status :: 4 - Beta
Classifier: Intended Audience :: Developers
Classifier: Topic :: Utilities
Classifier: License :: OSI Approved :: GNU General Public License v3 (GPLv3)
Classifier: Programming Language :: Python :: 3
Classifier: Operating System :: OS Independent
License-File: LICENSE
